keystroke/__init__.py
keystroke/agent.py
keystroke/cli.py
keystroke/events.py
keystroke/llm_tools.py
keystroke/schemas.py
keystroke/settings.py
keystroke/utils.py
keystroke/tools/__init__.py
keystroke/tools/calculator.py
keystroke/tools/file_management.py
keystroke/tools/presigned_url.py
keystroke_agent-0.1.7.dist-info/METADATA
keystroke_agent-0.1.7.dist-info/WHEEL
keystroke_agent-0.1.7.dist-info/entry_points.txt
keystroke_agent-0.1.7.dist-info/licenses/LICENSE
keystroke_agent-0.1.7.dist-info/RECORD
