Metadata-Version: 2.4
Name: keystroke-agent
Version: 0.1.7
Summary: An AI-powered CLI assistant with AWS Bedrock integration, tool support, and customizable features for interactive conversations and task automation.
Project-URL: Homepage, https://github.com/thepuspak/keystroke-agent
Project-URL: Repository, https://github.com/thepuspak/keystroke-agent.git
Project-URL: Issues, https://github.com/thepuspak/keystroke-agent/issues
Project-URL: Changelog, https://github.com/thepuspak/keystroke-agent/blob/main/CHANGELOG.md
Author-email: Puspak Rout <thepuspak@gmail.com>
License-File: LICENSE
Keywords: ai-assistant,async,aws,bedrock,chatbot,claude,cli,llm,terminal-ui,tools
Classifier: Development Status :: 3 - Alpha
Classifier: Framework :: AsyncIO
Classifier: Intended Audience :: Developers
Classifier: License :: OSI Approved :: MIT License
Classifier: Natural Language :: English
Classifier: Operating System :: OS Independent
Classifier: Programming Language :: Python :: 3
Classifier: Programming Language :: Python :: 3.12
Classifier: Topic :: Communications :: Chat
Classifier: Topic :: Software Development :: Libraries :: Python Modules
Requires-Python: >=3.12
Requires-Dist: boto3
Requires-Dist: build
Requires-Dist: fastapi
Requires-Dist: litellm
Requires-Dist: numpydoc
Requires-Dist: passlib
Requires-Dist: python-dotenv
Requires-Dist: python-jose
Requires-Dist: requests
Requires-Dist: rich
Requires-Dist: twine
Requires-Dist: uvicorn
Requires-Dist: websockets
